{"id":"coultervillelibrary","slug":"coultervillelibrary","title":"Help fight corruption in Coulterville","short":"Help fight corruption in Coulterville","description":"Help fight corruption in Coulterville - demand accountability, compliance, and transparency for the residents of the Coulterville Public Library District.","img":"https://fundlibraries.retool.com/api/file/ae88f38f-0b46-42e8-a010-00f960ad21a7","raised":0,"goal":8000,"category":"Public Libraries","location":"Coulterville, IL","city":"Coulterville","state":"IL","organization":"Coulterville Public Library District","status":"Active","start_date":"","end_date":"2025-11-01","created_at":"","updated_at":"2025-09-26T00:00:00.000Z","updates":[{"slug":"coultervillelibrary","date":"September 26, 2025","date_iso":"2025-09-26T00:00:00.000Z","content":""}]}